[{"id":2,"frutanombre":"manzana roja","frutaprecio":30,"frutaimg":"manzanaRoja.jpg","frutastock":0,"promo":1,"itemtipo":"fruta"},{"id":3,"frutanombre":"pera","frutaprecio":35,"frutaimg":"pera.jpg","frutastock":3,"promo":1,"itemtipo":"fruta"},{"id":5,"frutanombre":"uva","frutaprecio":50,"frutaimg":"uva.jpg","frutastock":8,"promo":1,"itemtipo":"fruta"},{"id":6,"frutanombre":"palta","frutaprecio":80,"frutaimg":"palta.jpg","frutastock":9,"promo":0,"itemtipo":"fruta"},{"id":7,"frutanombre":"naranja","frutaprecio":10,"frutaimg":"naranja.jpg","frutastock":15,"promo":0,"itemtipo":"fruta"},{"id":8,"frutanombre":"pepino","frutaprecio":15,"frutaimg":"pepino.jpg","frutastock":10,"promo":1,"itemtipo":"verdura"},{"id":9,"frutanombre":"cebolla","frutaprecio":25,"frutaimg":"cebolla.jpg","frutastock":20,"promo":1,"itemtipo":"verdura"},{"id":10,"frutanombre":"cebolla colorada","frutaprecio":30,"frutaimg":"cebollaColorada.jpg","frutastock":12,"promo":0,"itemtipo":"verdura"},{"id":11,"frutanombre":"frutilla","frutaprecio":50,"frutaimg":"frutilla.jpg","frutastock":12,"promo":1,"itemtipo":"fruta"},{"id":12,"frutanombre":"durazno","frutaprecio":30,"frutaimg":"durazno.jpg","frutastock":0,"promo":0,"itemtipo":"fruta"},{"id":13,"frutanombre":"coliflor","frutaprecio":40,"frutaimg":"coliflor.jpg","frutastock":5,"promo":0,"itemtipo":"verdura"},{"id":14,"frutanombre":"manzana Verde","frutaprecio":30,"frutaimg":"manzanaVerde.jpg","frutastock":4,"promo":1,"itemtipo":"fruta"},{"id":15,"frutanombre":"granada","frutaprecio":70,"frutaimg":"granada.jpg","frutastock":56,"promo":0,"itemtipo":"fruta"},{"id":16,"frutanombre":"repollo colorado","frutaprecio":39,"frutaimg":"repolloColorado.jpg","frutastock":30,"promo":0,"itemtipo":"verdura"},{"id":17,"frutanombre":"papa","frutaprecio":20,"frutaimg":"papa.jpg","frutastock":30,"promo":0,"itemtipo":"verdura"},{"id":18,"frutanombre":"pimiento rojo","frutaprecio":20,"frutaimg":"pimientoRojo.jpg","frutastock":23,"promo":0,"itemtipo":"verdura"},{"id":19,"frutanombre":"remolacha","frutaprecio":15,"frutaimg":"remolacha.jpg","frutastock":0,"promo":0,"itemtipo":"verdura"},{"id":20,"frutanombre":"berenjena","frutaprecio":45,"frutaimg":"berenjena.jpg","frutastock":2,"promo":1,"itemtipo":"verdura"},{"id":21,"frutanombre":"zanahoria","frutaprecio":26,"frutaimg":"zanahoria.jpg","frutastock":5,"promo":1,"itemtipo":"verdura"},{"id":22,"frutanombre":"sandia","frutaprecio":3,"frutaimg":"sandia.jpg","frutastock":6,"promo":1,"itemtipo":"fruta"},{"id":23,"frutanombre":"limon","frutaprecio":50,"frutaimg":"limon.jpg","frutastock":90,"promo":0,"itemtipo":"fruta"},{"id":24,"frutanombre":"ajo","frutaprecio":4,"frutaimg":"ajo.jpg","frutastock":10,"promo":1,"itemtipo":"verdura"}]